[
  {
    "Text": "white00",
    "Translation": ""
  },
  {
    "Text": "white00",
    "Translation": ""
  },
  {
    "Text": [
      "……ランディ、お前は\u0001",
      "あの《大樹》に向かうんだな？\u0002"
    ],
    "Translation": ""
  },
  {
    "Text": [
      "#00300F",
      "はは、よく分かるなぁ。\u0001",
      "さすがドレイク・オーナーだぜ。\u0002"
    ],
    "Translation": ""
  },
  {
    "Text": [
      "フン、お前との付き合いも\u0001",
      "短くはないからな。\u0002"
    ],
    "Translation": ""
  },
  {
    "Text": [
      "……ランディ、お前には\u0001",
      "今までツケで飲んだ分の代金が\u0001",
      "まだ残ってるんだ。\u0002"
    ],
    "Translation": ""
  },
  {
    "Text": [
      "絶対に無事に帰ってこねえと、\u0001",
      "承知しねえからな。\u0002"
    ],
    "Translation": ""
  },
  {
    "Text": [
      "#00304F",
      "……ああ、分かった。\u0002",
      "\u0003",
      "#00309F",
      "そのうちキッチリ返すから\u0001",
      "安心しとけっつの。\u0002"
    ],
    "Translation": ""
  },
  {
    "Text": [
      "#00002F",
      "（はは……この２人って\u0001",
      "  通じ合うものがあるんだろうな。）\u0002"
    ],
    "Translation": ""
  },
  {
    "Text": [
      "今まさに、クロスベルに試練の時が\u0001",
      "訪れているのかもしれません。\u0002"
    ],
    "Translation": ""
  },
  {
    "Text": [
      "……皆さん、どうかランディを\u0001",
      "よろしくお願いいたします。\u0002"
    ],
    "Translation": ""
  },
  {
    "Text": [
      "そいつが今まで\u0001",
      "ツケで飲んだ分の代金が、\u0001",
      "まだ残っていますから。\u0002"
    ],
    "Translation": ""
  },
  {
    "Text": [
      "#00003F",
      "ええ、お任せください。\u0002"
    ],
    "Translation": ""
  },
  {
    "Text": [
      "#00309F",
      "そのうちキッチリ返すから\u0001",
      "安心しとけっつの。\u0002"
    ],
    "Translation": ""
  },
  {
    "Text": [
      "今まさに、クロスベルに試練の時が\u0001",
      "訪れているのかもしれません。\u0002"
    ],
    "Translation": ""
  },
  {
    "Text": [
      "……皆さん、どうかランディを\u0001",
      "よろしくお願いいたします。\u0002"
    ],
    "Translation": ""
  },
  {
    "Text": "おお、これは皆さん……\u0002",
    "Translation": ""
  },
  {
    "Text": [
      "#00300F",
      "久しぶりだな、オーナー。\u0001",
      "元気にしてたみてえじゃねえか？\u0002"
    ],
    "Translation": ""
  },
  {
    "Text": "お前もな、ランディ。\u0002",
    "Translation": ""
  },
  {
    "Text": [
      "マインツでのレジスタンス活動に\u0001",
      "身を投じていると聞いたが、\u0001",
      "お仲間と合流できたようでなによりだ。\u0002"
    ],
    "Translation": ""
  },
  {
    "Text": [
      "#00000F",
      "こちらには\u0001",
      "被害などは出ていませんか？\u0002"
    ],
    "Translation": ""
  },
  {
    "Text": "ええ、今のところは。\u0002",
    "Translation": ""
  },
  {
    "Text": [
      "皆さんも、市内を回られているなら\u0001",
      "十分にお気をつけてください。\u0002"
    ],
    "Translation": ""
  },
  {
    "Text": [
      "#00300F",
      "ああ、そっちもな。\u0002"
    ],
    "Translation": ""
  },
  {
    "Text": [
      "しかし、戒厳令から\u0001",
      "営業を縮小していて正解でした。\u0002"
    ],
    "Translation": ""
  },
  {
    "Text": [
      "この少人数なら店の備蓄でも\u0001",
      "しばらくは持ちこたえるでしょう。\u0002"
    ],
    "Translation": ""
  },
  {
    "Text": [
      "どうかこちらはご心配なく。\u0001",
      "皆さんは皆さんの仕事に\u0001",
      "あたられてください。\u0002"
    ],
    "Translation": ""
  },
  {
    "Text": [
      "この少人数なら店の備蓄でも\u0001",
      "しばらくは持ちこたえるでしょう。\u0002"
    ],
    "Translation": ""
  },
  {
    "Text": [
      "どうかこちらはご心配なく。\u0001",
      "皆さんは皆さんの仕事に\u0001",
      "あたられてください。\u0002"
    ],
    "Translation": ""
  },
  {
    "Text": [
      "ふむ……朝から見慣れない\u0001",
      "制服を着た連中がいると思ったら、\u0001",
      "あれが国防軍の兵士ですか。\u0002"
    ],
    "Translation": ""
  },
  {
    "Text": [
      "いかにも\u0001",
      "準備万端という感じですが……\u0002"
    ],
    "Translation": ""
  },
  {
    "Text": [
      "クロイス氏は一体いつ頃から\u0001",
      "このシナリオを\u0001",
      "思い描いてたんですかね。\u0002"
    ],
    "Translation": ""
  },
  {
    "Text": [
      "思えばまだ、あの住民投票から\u0001",
      "１週間しか経っていませんが……\u0002"
    ],
    "Translation": ""
  },
  {
    "Text": [
      "クロイス氏は一体いつ頃から\u0001",
      "このシナリオを\u0001",
      "思い描いてたんですかね。\u0002"
    ],
    "Translation": ""
  },
  {
    "Text": [
      "おう、ランディ。\u0001",
      "よく分かんねえが、何か\u0001",
      "吹っ切れた顔してやがんな。\u0002"
    ],
    "Translation": ""
  },
  {
    "Text": [
      "店の方はこの状況で\u0001",
      "閑古鳥が鳴いてるっつうのに、\u0001",
      "一体どういうつもりだ？\u0002"
    ],
    "Translation": ""
  },
  {
    "Text": [
      "#00305F",
      "ん、別にどこも\u0001",
      "変わっちゃいねえと思うが？\u0002",
      "\u0003",
      "#00309F",
      "さてはオーナー、俺がちょっと\u0001",
      "店に顔を出さなかったからって\u0001",
      "早くも寂しがってんだな？\u0002"
    ],
    "Translation": ""
  },
  {
    "Text": [
      "フン、バカ言え。\u0001",
      "口うるさいのがいなくて、\u0001",
      "逆にせいせいしてたくらいだ。\u0002"
    ],
    "Translation": ""
  },
  {
    "Text": [
      "とにかく、お前にはこれまで\u0001",
      "色んなモンを貸して来てんだ。\u0002"
    ],
    "Translation": ""
  },
  {
    "Text": [
      "そいつらを全部返し終えるまで、\u0001",
      "勝手にバックレんじゃねえぞ。\u0002"
    ],
    "Translation": ""
  },
  {
    "Text": [
      "#00300F",
      "ハ、言われなくても分かってら。\u0002"
    ],
    "Translation": ""
  },
  {
    "Text": [
      "#00000F",
      "（この２人、何だかんだで\u0001",
      "  仲が良いんだよな。）\u0002"
    ],
    "Translation": ""
  },
  {
    "Text": [
      "#00100F",
      "（ええ、まるで子供みたいにね。）\u0002"
    ],
    "Translation": ""
  },
  {
    "Text": [
      "とにかくランディ、\u0001",
      "俺がお前にこれまで色んなモンを\u0001",
      "貸して来たことを忘れんなよ。\u0002"
    ],
    "Translation": ""
  },
  {
    "Text": [
      "期限は特に設けねえが、\u0001",
      "いつか必ず返してもらうからな。\u0002"
    ],
    "Translation": ""
  },
  {
    "Text": [
      "私がヤツにしてやれるのは\u0001",
      "せいぜい飲む場所を\u0001",
      "与えてやる程度のこと……\u0002"
    ],
    "Translation": ""
  },
  {
    "Text": [
      "ですが皆さんならば\u0001",
      "本当の意味でヤツの力になれる、\u0001",
      "そんな気がするのです。\u0002"
    ],
    "Translation": ""
  },
  {
    "Text": [
      "皆さん、ランディのこと……\u0001",
      "どうかよろしくお願いします。\u0002"
    ],
    "Translation": ""
  },
  {
    "Text": [
      "皆さんならば\u0001",
      "本当の意味でヤツの力になれる、\u0001",
      "そんな気がするのです。\u0002"
    ],
    "Translation": ""
  },
  {
    "Text": [
      "皆さん、ランディのこと……\u0001",
      "どうかよろしくお願いします。\u0002"
    ],
    "Translation": ""
  },
  {
    "Text": [
      "明日はいよいよ\u0001",
      "リニューアル舞台の公開日ですね。\u0002"
    ],
    "Translation": ""
  },
  {
    "Text": [
      "何でも今度の舞台では\u0001",
      "あのリーシャ・マオに次ぐ\u0001",
      "大型新人がデビューするとか。\u0002"
    ],
    "Translation": ""
  },
  {
    "Text": [
      "フフ、アルカンシェルの話題は\u0001",
      "いつも我々を楽しませてくれますね。\u0002"
    ],
    "Translation": ""
  },
  {
    "Text": [
      "何でも今度の舞台では\u0001",
      "あのリーシャ・マオに次ぐ\u0001",
      "大型新人がデビューするとか。\u0002"
    ],
    "Translation": ""
  },
  {
    "Text": [
      "フフ、アルカンシェルの話題は\u0001",
      "いつも我々を楽しませてくれますね。\u0002"
    ],
    "Translation": ""
  },
  {
    "Text": [
      "いらっしゃいませ。\u0001",
      "カジノハウス《バルカ》へようこそ。\u0002"
    ],
    "Translation": ""
  },
  {
    "Text": [
      "頭を休めたい時は、どうぞこちらの\u0001",
      "バーカウンターをご利用下さいませ。\u0002"
    ],
    "Translation": ""
  },
  {
    "Text": [
      "アルコール類はもちろん、\u0001",
      "コーヒーなどもお出しできますよ？\u0002"
    ],
    "Translation": ""
  },
  {
    "Text": [
      "頭を休めたい時は、どうぞこちらの\u0001",
      "バーカウンターをご利用下さいませ。\u0002"
    ],
    "Translation": ""
  },
  {
    "Text": [
      "アルコール類はもちろん、\u0001",
      "コーヒーなどもお出しできますよ？\u0002"
    ],
    "Translation": ""
  },
  {
    "Text": [
      "国家独立の是非、ですか……\u0001",
      "裏社会の勢力図が今も蠢く中にあって、\u0001",
      "この問題はまたとんでもないですな。\u0002"
    ],
    "Translation": ""
  },
  {
    "Text": [
      "住民投票の結果が即何かの動きに\u0001",
      "つながるとは到底思えませんが……\u0001",
      "問題は２大国の動向ですね。\u0002"
    ],
    "Translation": ""
  },
  {
    "Text": [
      "下手をすれば、クロスベルの立場は\u0001",
      "今以上に悪くなりなねませんからね。\u0002"
    ],
    "Translation": ""
  },
  {
    "Text": [
      "住民投票の結果が即何かの動きに\u0001",
      "つながるとは到底思えませんが……\u0001",
      "問題は２大国の動向ですね。\u0002"
    ],
    "Translation": ""
  },
  {
    "Text": [
      "下手をすれば、クロスベルの立場は\u0001",
      "今以上に悪くなりかねませんからね。\u0002"
    ],
    "Translation": ""
  },
  {
    "Text": [
      "ふむ、何だか少々\u0001",
      "１階の方が騒がしいみたいですね。\u0002"
    ],
    "Translation": ""
  },
  {
    "Text": [
      "これ以上うるさくするようでしたら、\u0001",
      "お引取り願いたい所ですが……\u0002"
    ],
    "Translation": ""
  },
  {
    "Text": [
      "いらっしゃいませ。\u0001",
      "カジノハウス《バルカ》へようこそ。\u0002"
    ],
    "Translation": ""
  },
  {
    "Text": [
      "身も心も溶かしてしまう……\u0001",
      "甘いカクテルはいかがですかな？\u0002"
    ],
    "Translation": ""
  },
  {
    "Text": [
      "オルキスタワーの除幕式は\u0001",
      "盛況の内に終わったようですね。\u0002"
    ],
    "Translation": ""
  },
  {
    "Text": "フフ、私も後で見るのが楽しみですよ。\u0002",
    "Translation": ""
  },
  {
    "Text": [
      "おう、ランディ。\u0001",
      "昨日の酒はもう抜けたのか？\u0002"
    ],
    "Translation": ""
  },
  {
    "Text": [
      "#00302F",
      "ハ、当たり前だろ。\u0001",
      "この俺があんなケチな量の酒を\u0001",
      "次の日に残すと思ったか？\u0002"
    ],
    "Translation": ""
  },
  {
    "Text": [
      "フン、お前は相変わらず\u0001",
      "口の減らんヤツだな。\u0002"
    ],
    "Translation": ""
  },
  {
    "Text": [
      "復帰祝いとはいえ、\u0001",
      "奢るんじゃなかったぜ。\u0002"
    ],
    "Translation": ""
  },
  {
    "Text": [
      "#00304F",
      "はは、すまねえな。\u0001",
      "だが感謝はしてんだぜ？\u0002",
      "\u0003",
      "#00300F",
      "ってわけでオーナー、\u0001",
      "また機会があったら頼むぜ。\u0002"
    ],
    "Translation": ""
  },
  {
    "Text": "フン、勝手言いやがって。\u0002",
    "Translation": ""
  },
  {
    "Text": [
      "#00100F",
      "（ランディ、ちゃっかり\u0001",
      "  顔を出していたみたいね。）\u0002"
    ],
    "Translation": ""
  },
  {
    "Text": [
      "#00000F",
      "（ああ、そうだな。）\u0002"
    ],
    "Translation": ""
  },
  {
    "Text": [
      "ま、また奢ってもらいたきゃ\u0001",
      "その減らず口を治すんだな。\u0002"
    ],
    "Translation": ""
  },
  {
    "Text": [
      "そうすりゃ\u0001",
      "考えてやらんこともない。\u0002"
    ],
    "Translation": ""
  },
  {
    "Text": [
      "#00304F",
      "へいへい、\u0001",
      "まあゼンショしておくぜ。\u0002"
    ],
    "Translation": ""
  },
  {
    "Text": [
      "ま、また奢ってもらいたきゃ\u0001",
      "その減らず口を治すんだな。\u0002"
    ],
    "Translation": ""
  },
  {
    "Text": [
      "そうすりゃ\u0001",
      "考えてやらんこともない。\u0002"
    ],
    "Translation": ""
  },
  {
    "Text": [
      "最近、ルバーチェの代わりに\u0001",
      "みかじめ料を寄こせという小物が\u0001",
      "現れるようになりましてね。\u0002"
    ],
    "Translation": ""
  },
  {
    "Text": [
      "今は相手にしていないのですが、\u0001",
      "この状況が続けば色々と\u0001",
      "面倒な事になって来るでしょう。\u0002"
    ],
    "Translation": ""
  },
  {
    "Text": [
      "やれやれ、早くどこでもいいから\u0001",
      "ルバーチェ跡の一帯を\u0001",
      "引き継いで欲しいものですよ。\u0002"
    ],
    "Translation": ""
  },
  {
    "Text": [
      "#10103F",
      "（ルバーチェが消えた影響が\u0001",
      "  こういう所にも……）\u0002"
    ],
    "Translation": ""
  },
  {
    "Text": [
      "#00000F",
      "（これも紛いなりに保っていた\u0001",
      "  秩序の１つって所だろうな。）\u0002"
    ],
    "Translation": ""
  },
  {
    "Text": [
      "今はまだ、どこの連中も比較的\u0001",
      "大人しくはしているようですが……\u0001",
      "流石にこの状況が続くと面倒です。\u0002"
    ],
    "Translation": ""
  },
  {
    "Text": [
      "やれやれ、早くどこでもいいから\u0001",
      "ルバーチェ跡の一帯を\u0001",
      "引き継いで欲しいものですよ。\u0002"
    ],
    "Translation": ""
  },
  {
    "Text": [
      "ランディのヤツは警備隊に混じって\u0001",
      "うまくやれているんですかね。\u0002"
    ],
    "Translation": ""
  },
  {
    "Text": [
      "フフ、昔みたいに情けないことを\u0001",
      "言っていなければ良いのですが。\u0002"
    ],
    "Translation": ""
  },
  {
    "Text": [
      "特務支援課の皆さん……\u0001",
      "それにワジさんじゃありませんか。\u0002"
    ],
    "Translation": ""
  },
  {
    "Text": "何とも、珍しい組み合わせですね。\u0002",
    "Translation": ""
  },
  {
    "Text": [
      "#10300F",
      "ああ、オーナー。\u0001",
      "実はこの度、特務支援課に\u0001",
      "配属されることが決まってね。\u0002",
      "\u0003",
      "詳細は省くけど、今後はひとつ\u0001",
      "そういうことでヨロシク頼むよ。\u0002"
    ],
    "Translation": ""
  },
  {
    "Text": [
      "なるほど、そうでしたか……\u0001",
      "フフ、かしこまりました。\u0002"
    ],
    "Translation": ""
  },
  {
    "Text": [
      "#00105F",
      "あ、あっさり受け入れるんですね。\u0002"
    ],
    "Translation": ""
  },
  {
    "Text": [
      "#00000F",
      "それもそうだけど……\u0001",
      "ワジ、当然のように\u0001",
      "オーナーと知り合いなんだな。\u0002"
    ],
    "Translation": ""
  },
  {
    "Text": [
      "#10304F",
      "まあ、ホストにとっては\u0001",
      "カジノを含めてここいら一帯は\u0001",
      "仕事場みたいなものだからね。\u0002",
      "\u0003",
      "#10300F",
      "逆にドレイク・オーナーと\u0001",
      "知り合いじゃないホストなんて\u0001",
      "モグリか三流なんじゃない？\u0002"
    ],
    "Translation": ""
  },
  {
    "Text": [
      "#10106F",
      "しれっと言うなあ……\u0002",
      "\u0003",
      "#10101F",
      "大体、その歳で\u0001",
      "この界隈を遊び回るなんて\u0001",
      "よくないことなんだからね。\u0002",
      "\u0003",
      "#10103F",
      "この機会に少しは……\u0002"
    ],
    "Translation": ""
  },
  {
    "Text": [
      "#10304F",
      "フフ、相変わらず堅いね。\u0002",
      "\u0003",
      "まあ、そういう所も\u0001",
      "君の魅力の内のひとつだと思うけど㈱\u0002"
    ],
    "Translation": ""
  },
  {
    "Text": [
      "#10106F",
      "はあ、何だかもう\u0001",
      "どうでもよくなってきた。\u0002"
    ],
    "Translation": ""
  },
  {
    "Text": [
      "#00106F",
      "分かるわ、その気持ち。\u0002"
    ],
    "Translation": ""
  },
  {
    "Text": [
      "そういえば皆さん、\u0001",
      "ランディのヤツはまだ\u0001",
      "復帰していないのですね？\u0002"
    ],
    "Translation": ""
  },
  {
    "Text": [
      "前に本人から古巣の警備隊に\u0001",
      "顔を出して来ると聞きましたが。\u0002"
    ],
    "Translation": ""
  },
  {
    "Text": [
      "#00000F",
      "ええ、もうしばらくすれば\u0001",
      "合流できると思うんですが。\u0002"
    ],
    "Translation": ""
  },
  {
    "Text": [
      "なるほど、ではまあヤツが\u0001",
      "復帰した折には店に顔を出すよう\u0001",
      "お伝え頂けますか？\u0002"
    ],
    "Translation": ""
  },
  {
    "Text": [
      "復帰祝いにワインの一本でも\u0001",
      "用意してやる、と言っていたと。\u0002"
    ],
    "Translation": ""
  },
  {
    "Text": [
      "#00000F",
      "はい、分かりました。\u0002"
    ],
    "Translation": ""
  },
  {
    "Text": [
      "#00100F",
      "ちゃんと伝えておきますね。\u0002"
    ],
    "Translation": ""
  },
  {
    "Text": [
      "話をする\u0001",
      "交換をする\u0001",
      "やめる\u0001"
    ],
    "Translation": ""
  },
  {
    "Text": [
      "ようこそ、\u0001",
      "カジノハウス《バルカ》へ～！\u0002"
    ],
    "Translation": ""
  },
  {
    "Text": [
      "たっくさん遊んでいって、\u0001",
      "不安を吹き飛ばしてちょうだい☆\u0002"
    ],
    "Translation": ""
  },
  {
    "Text": [
      "こんな時だけど、\u0001",
      "ウチも通常通り営業よん。\u0002"
    ],
    "Translation": ""
  },
  {
    "Text": [
      "たっくさん遊んでいって、\u0001",
      "不安を吹き飛ばしてちょうだい☆\u0002"
    ],
    "Translation": ""
  },
  {
    "Text": [
      "ううっ、正直怖いけど……\u0001",
      "ガレッティさんとエリンデさんが\u0001",
      "お休みでよかったわ。\u0002"
    ],
    "Translation": ""
  },
  {
    "Text": [
      "オーナーが頑張ってるし、\u0001",
      "あたしもしっかりしなくちゃね。\u0002"
    ],
    "Translation": ""
  },
  {
    "Text": [
      "ガレッティさんとエリンデさんが\u0001",
      "お休みだから、１Ｆでは遊べないけど……\u0002"
    ],
    "Translation": ""
  },
  {
    "Text": [
      "うちの景品にも役立つものが\u0001",
      "あるかもしれないから、\u0001",
      "いつも通り利用してってね！\u0002"
    ],
    "Translation": ""
  },
  {
    "Text": [
      "う～ん、まさか突然戦争に\u0001",
      "なったりはしないわよね～？\u0002"
    ],
    "Translation": ""
  },
  {
    "Text": [
      "これを受けて、２大国は\u0001",
      "どんな声明を出すのかしら？\u0002"
    ],
    "Translation": ""
  },
  {
    "Text": "う～ん、住民投票か～。\u0002",
    "Translation": ""
  },
  {
    "Text": [
      "投票所は何箇所かあるらしいけど、\u0001",
      "やっぱ行くならオルキスタワーよね～☆\u0002"
    ],
    "Translation": ""
  },
  {
    "Text": [
      "う～ん、クロスベル市外の\u0001",
      "出来事とは言え、マインツの事は\u0001",
      "他人事じゃないよね～。\u0002"
    ],
    "Translation": ""
  },
  {
    "Text": "早く無事に解決して欲しいわぁ。\u0002",
    "Translation": ""
  },
  {
    "Text": [
      "アルカンシェルの公演、\u0001",
      "ついに明日の公開ね～。\u0002"
    ],
    "Translation": ""
  },
  {
    "Text": [
      "きっとまた、ウチにも\u0001",
      "お客さんが流れてくるはずよ。\u0002"
    ],
    "Translation": ""
  },
  {
    "Text": "うふ、楽しみね～㈱\u0002",
    "Translation": ""
  },
  {
    "Text": [
      "アルカンシェルを観終わって\u0001",
      "ウチに来る人って結構多いのよ。\u0002"
    ],
    "Translation": ""
  },
  {
    "Text": "うふ、楽しみね～㈱\u0002",
    "Translation": ""
  },
  {
    "Text": [
      "メダルがなくなったら\u0001",
      "いつでも言ってね～☆\u0002"
    ],
    "Translation": ""
  },
  {
    "Text": [
      "ミラがなくなったら、\u0001",
      "ＩＢＣへレッツゴー！\u0002"
    ],
    "Translation": ""
  },
  {
    "Text": "ようこそ《バルカ》へ～！\u0002",
    "Translation": ""
  },
  {
    "Text": [
      "うふふ、今日もたっぷり\u0001",
      "遊んで行ってね～☆\u0002"
    ],
    "Translation": ""
  },
  {
    "Text": [
      "あの３人組、\u0001",
      "お金持ちらしいけど\u0001",
      "随分感じが悪いのよね～。\u0002"
    ],
    "Translation": ""
  },
  {
    "Text": [
      "上から目線で誘われたけど、\u0001",
      "こっちから願い下げって感じ？\u0002"
    ],
    "Translation": ""
  },
  {
    "Text": [
      "通商会議も今日が\u0001",
      "いよいよ本番なんだってね。\u0002"
    ],
    "Translation": ""
  },
  {
    "Text": [
      "チェリーにはよく分かんないけど、\u0001",
      "とにかくうまく行って欲しいわ㈱\u0002"
    ],
    "Translation": ""
  },
  {
    "Text": [
      "ガンツさん、\u0001",
      "今日もまた懲りずにスロットに\u0001",
      "精を出しているみたいね～。\u0002"
    ],
    "Translation": ""
  },
  {
    "Text": [
      "数ヶ月前に見せたツキは\u0001",
      "一体何だったんだろうってくらい\u0001",
      "ヘボヘボだけど……\u0002"
    ],
    "Translation": ""
  },
  {
    "Text": [
      "ガンツさん、もしかしたら\u0001",
      "あの時に一生分のツキを\u0001",
      "使い果たしちゃったのかも～？\u0002"
    ],
    "Translation": ""
  },
  {
    "Text": [
      "ガンツさん、もしかしたら\u0001",
      "あの時に一生分のツキを\u0001",
      "使い果たしちゃったのかも～？\u0002"
    ],
    "Translation": ""
  },
  {
    "Text": [
      "ま、それでもたま～に\u0001",
      "当ててはいるみたいだから\u0001",
      "そこまでじゃないんだろうけど。\u0002"
    ],
    "Translation": ""
  },
  {
    "Text": "あ、ランディさんだ～。\u0002",
    "Translation": ""
  },
  {
    "Text": [
      "もー、最近どこへ行ってたのよ～。\u0001",
      "ダメじゃない、もっと遊ばなきゃ。\u0002"
    ],
    "Translation": ""
  },
  {
    "Text": [
      "#00304F",
      "全くだ、悪ぃなチェリーちゃん。\u0002",
      "\u0003",
      "#00309F",
      "そんじゃ早速、仕事を切り上げて――\u0002"
    ],
    "Translation": ""
  },
  {
    "Text": [
      "#00009F",
      "なあ、ランディ。\u0002"
    ],
    "Translation": ""
  },
  {
    "Text": [
      "#00109F",
      "ふふ、もちろん冗談よね？\u0002"
    ],
    "Translation": ""
  },
  {
    "Text": [
      "#00306F",
      "あ、ああ……\u0001",
      "ってか笑顔が怖ぇぞ、２人とも。\u0002"
    ],
    "Translation": ""
  },
  {
    "Text": [
      "#00109F",
      "ねえ、ランディ。\u0001",
      "さっきも言ったと思うけど……\u0002"
    ],
    "Translation": ""
  },
  {
    "Text": [
      "#00306F",
      "あ、ああ……\u0001",
      "だから冗談だって。\u0002"
    ],
    "Translation": ""
  },
  {
    "Text": [
      "#10106F",
      "（ランディ先輩……\u0001",
      "  本当に懲りないですね。）\u0002"
    ],
    "Translation": ""
  },
  {
    "Text": [
      "ランディさん、\u0001",
      "またバンバン顔を見せてよね～。\u0002"
    ],
    "Translation": ""
  },
  {
    "Text": [
      "そうでないと、\u0001",
      "チェリーつまんないんだからぁ。\u0002"
    ],
    "Translation": ""
  },
  {
    "Text": [
      "ジメジメうっとうしい雨は\u0001",
      "カジノで吹き飛ばそ～☆\u0002"
    ],
    "Translation": ""
  },
  {
    "Text": "今日もバンバン遊んでね～！\u0002",
    "Translation": ""
  },
  {
    "Text": [
      "さっき突然、ふらっと\u0001",
      "レクターさんがやって来て\u0001",
      "２階に上がっていったの。\u0002"
    ],
    "Translation": ""
  },
  {
    "Text": [
      "ふふ、数ヶ月ぶりに見たけど、\u0001",
      "相変わらず変わった人よね。\u0002"
    ],
    "Translation": ""
  },
  {
    "Text": [
      "#00101F",
      "ロイド……！\u0002"
    ],
    "Translation": ""
  },
  {
    "Text": [
      "#00001F",
      "ああ、今度こそ逃がさないぞ。\u0002"
    ],
    "Translation": ""
  },
  {
    "Text": [
      "さっき突然、ふらっと\u0001",
      "レクターさんがやって来て\u0001",
      "２階に上がっていったの。\u0002"
    ],
    "Translation": ""
  },
  {
    "Text": [
      "ふふ、数ヶ月ぶりに見たけど、\u0001",
      "相変わらず変わった人よね。\u0002"
    ],
    "Translation": ""
  },
  {
    "Text": "ようこそ《バルカ》へ～！\u0002",
    "Translation": ""
  },
  {
    "Text": [
      "ここはメダルや\u0001",
      "景品の交換カウンターよ㈱\u0002"
    ],
    "Translation": ""
  },
  {
    "Text": [
      "バンバン遊んで\u0001",
      "いい景品をゲットしてね～☆\u0002"
    ],
    "Translation": ""
  },
  {
    "Text": [
      "ここはメダルや\u0001",
      "景品の交換カウンターよ㈱\u0002"
    ],
    "Translation": ""
  },
  {
    "Text": [
      "バンバン遊んで\u0001",
      "いい景品をゲットしてね～☆\u0002"
    ],
    "Translation": ""
  },
  {
    "Text": [
      "話をする\u0001",
      "ポーカーで遊ぶ\u0001",
      "ブラックジャックで遊ぶ\u0001",
      "やめる\u0001"
    ],
    "Translation": ""
  },
  {
    "Text": [
      "常連のレイタロッサさんが\u0001",
      "帰国されてしまって、\u0001",
      "私も寂しい限りです。\u0002"
    ],
    "Translation": ""
  },
  {
    "Text": [
      "彼女とのスリル溢れる勝負は\u0001",
      "毎日の楽しみでしたから。\u0002"
    ],
    "Translation": ""
  },
  {
    "Text": [
      "クロスベルが平和を取り戻したら、\u0001",
      "また遊びに来てほしいものです。\u0002"
    ],
    "Translation": ""
  },
  {
    "Text": [
      "常連のレイタロッサさん……\u0001",
      "クロスベルが平和を取り戻したら、\u0001",
      "また遊びに来てほしいものですね。\u0002"
    ],
    "Translation": ""
  },
  {
    "Text": [
      "あのような得体のしれない大樹が\u0001",
      "現れている間は、難しいでしょうが……\u0002"
    ],
    "Translation": ""
  },
  {
    "Text": [
      "今日は朝から導力鉄道の運行が\u0001",
      "制限されているみたいですね。\u0002"
    ],
    "Translation": ""
  },
  {
    "Text": [
      "クロスベルにいる帝国・\u0001",
      "共和国人には本国への帰国勧告も\u0001",
      "発令されたとのことですが……\u0002"
    ],
    "Translation": ""
  },
  {
    "Text": [
      "事態は我々が\u0001",
      "思っている以上のスピードで\u0001",
      "動いているのかもしれませんね。\u0002"
    ],
    "Translation": ""
  },
  {
    "Text": [
      "クロスベルにいる帝国・\u0001",
      "共和国人には本国への帰国勧告も\u0001",
      "発令されたとのことですが……\u0002"
    ],
    "Translation": ""
  },
  {
    "Text": [
      "事態は我々が\u0001",
      "思っている以上のスピードで\u0001",
      "動いているのかもしれませんね。\u0002"
    ],
    "Translation": ""
  },
  {
    "Text": [
      "今も地面などに残る焦げ跡を見ると……\u0001",
      "襲撃時のことが思い起こされます。\u0002"
    ],
    "Translation": ""
  },
  {
    "Text": [
      "幸いにも武装集団が\u0001",
      "当店に乗り込んで来ることは\u0001",
      "ありませんでしたが……\u0002"
    ],
    "Translation": ""
  },
  {
    "Text": [
      "もしここが襲われていたら\u0001",
      "私たちもどうなっていたことか……\u0001",
      "考えただけで恐ろしいですね。\u0002"
    ],
    "Translation": ""
  },
  {
    "Text": [
      "幸いにも武装集団が\u0001",
      "当店に乗り込んで来ることは\u0001",
      "ありませんでしたが……\u0002"
    ],
    "Translation": ""
  },
  {
    "Text": [
      "もしここが襲われていたら\u0001",
      "私たちもどうなっていたことか……\u0001",
      "考えただけで恐ろしいですね。\u0002"
    ],
    "Translation": ""
  },
  {
    "Text": [
      "既に噂もあるようですが……\u0001",
      "背後に帝国政府がいると考えるのが\u0001",
      "自然といった所でしょうか。\u0002"
    ],
    "Translation": ""
  },
  {
    "Text": [
      "とにかく、次に帝国が\u0001",
      "どう出てくるかが気になる所ですね。\u0002"
    ],
    "Translation": ""
  },
  {
    "Text": [
      "国家独立の是非……\u0001",
      "確か住民投票の期日も\u0001",
      "近づいて来ていましたね。\u0002"
    ],
    "Translation": ""
  },
  {
    "Text": [
      "ふむ、どちらの選択が\u0001",
      "よりベターな結果を生みそうか……\u0001",
      "もう少し見極めたい所ですね。\u0002"
    ],
    "Translation": ""
  },
  {
    "Text": [
      "退屈な人生と刺激に満ちた人生は、\u0001",
      "一体どちらが幸せなのでしょう……\u0002"
    ],
    "Translation": ""
  },
  {
    "Text": "ふふ、お客様はどうお考えですか？\u0002",
    "Translation": ""
  },
  {
    "Text": [
      "負けが込んだとふてくされるのは\u0001",
      "二流のやることでございます。\u0002"
    ],
    "Translation": ""
  },
  {
    "Text": [
      "お客様がたには、是非とも\u0001",
      "誠意を持って賭け事に望んで\u0001",
      "欲しいものでございますね。\u0002"
    ],
    "Translation": ""
  },
  {
    "Text": [
      "（さっきから大声で騒いだり、\u0001",
      "  他のお客様に迷惑をかけたり……）\u0002"
    ],
    "Translation": ""
  },
  {
    "Text": [
      "（あちらのお客様は、\u0001",
      "  少々マナーがなっていませんね。）\u0002"
    ],
    "Translation": ""
  },
  {
    "Text": [
      "（行為が過ぎるようなら\u0001",
      "  厳重に注意しておかなければ。）\u0002"
    ],
    "Translation": ""
  },
  {
    "Text": [
      "（いくらカジノとはいえ、\u0001",
      "  この場所にはこの場所なりの\u0001",
      "  ルールとマナーがございます。）\u0002"
    ],
    "Translation": ""
  },
  {
    "Text": [
      "（行為が過ぎるようなら\u0001",
      "  厳重に注意しておかなければ。）\u0002"
    ],
    "Translation": ""
  },
  {
    "Text": [
      "ディーター市長の\u0001",
      "ギャンブルセンスですか……\u0001",
      "はてさて、どうなんでしょう？\u0002"
    ],
    "Translation": ""
  },
  {
    "Text": [
      "こうした遊びもスマートに\u0001",
      "こなしそうな印象ではありますが。\u0002"
    ],
    "Translation": ""
  },
  {
    "Text": [
      "今日はガンツさんが\u0001",
      "お見えになっているようですね。\u0002"
    ],
    "Translation": ""
  },
  {
    "Text": [
      "いつぞやの強運ぶりには\u0001",
      "本当に驚かされましたが……\u0002"
    ],
    "Translation": ""
  },
  {
    "Text": [
      "今ではすっかり、元の冴えない\u0001",
      "週末ギャンブラーに逆戻りですね。\u0002"
    ],
    "Translation": ""
  },
  {
    "Text": [
      "ガンツさんのいつぞやの\u0001",
      "強運ぶりには本当に\u0001",
      "驚かされましたが……\u0002"
    ],
    "Translation": ""
  },
  {
    "Text": [
      "今ではすっかり、元の冴えない\u0001",
      "週末ギャンブラーに逆戻りですね。\u0002"
    ],
    "Translation": ""
  },
  {
    "Text": [
      "かの高級クラブ\u0001",
      "《ノイエ＝ブラン》がこの度\u0001",
      "新装開店したそうですね。\u0002"
    ],
    "Translation": ""
  },
  {
    "Text": [
      "私のような者にはとても\u0001",
      "手の届かない場所ですが……\u0001",
      "一度は行ってみたいものです。\u0002"
    ],
    "Translation": ""
  },
  {
    "Text": [
      "いやはや、レイタロッサ様は\u0001",
      "本当に不敵でいらっしゃる。\u0002"
    ],
    "Translation": ""
  },
  {
    "Text": [
      "ギャンブルは過程より結果……\u0001",
      "最後に笑った者の勝ちですからね。\u0002"
    ],
    "Translation": ""
  },
  {
    "Text": [
      "いらっしゃいませ。\u0001",
      "こちらはカード台でございます。\u0002"
    ],
    "Translation": ""
  },
  {
    "Text": "宜しければ、一勝負いかがですか？\u0002",
    "Translation": ""
  },
  {
    "Text": [
      "……残念、この勝負、\u0001",
      "私の勝ちでございます。\u0002"
    ],
    "Translation": ""
  },
  {
    "Text": [
      "ふふ、やるじゃない。\u0001",
      "でも次はそうは行かないわよ㈱\u0002"
    ],
    "Translation": ""
  },
  {
    "Text": "フフ、お手柔らかに。\u0002",
    "Translation": ""
  },
  {
    "Text": [
      "話をする\u0001",
      "ルーレットで遊ぶ\u0001",
      "やめる\u0001"
    ],
    "Translation": ""
  },
  {
    "Text": [
      "こんな時にでも賭け事に来る……\u0001",
      "それは悪い事でも\u0001",
      "なんでもありませんわ。\u0002"
    ],
    "Translation": ""
  },
  {
    "Text": [
      "本来、不安な気持ちを紛らわせ、\u0001",
      "心を楽にしてくれるのが\u0001",
      "娯楽というものなのですから。\u0002"
    ],
    "Translation": ""
  },
  {
    "Text": [
      "どうか、不安な時こそ\u0001",
      "娯楽を楽しんでほしいものです。\u0002"
    ],
    "Translation": ""
  },
  {
    "Text": [
      "本来、不安な気持ちを紛らわせ、\u0001",
      "心を楽にしてくれるのが\u0001",
      "娯楽というものですわ。\u0002"
    ],
    "Translation": ""
  },
  {
    "Text": [
      "どうか、不安な時こそ\u0001",
      "娯楽を楽しんでほしいものです。\u0002"
    ],
    "Translation": ""
  },
  {
    "Text": [
      "クロスベルの独立問題も\u0001",
      "とうとう引き返せない所まで\u0001",
      "来てしまいましたね。\u0002"
    ],
    "Translation": ""
  },
  {
    "Text": [
      "ディーター大統領も\u0001",
      "何の勝算なしにここまでの事を\u0001",
      "するとは思えませんが……\u0002"
    ],
    "Translation": ""
  },
  {
    "Text": [
      "一体、どんなカードを\u0001",
      "用意しているのでしょうか？\u0002"
    ],
    "Translation": ""
  },
  {
    "Text": [
      "ディーター大統領も\u0001",
      "何の勝算なしにここまでの事を\u0001",
      "するとは思えませんが……\u0002"
    ],
    "Translation": ""
  },
  {
    "Text": [
      "一体、どんなカードを\u0001",
      "用意しているのでしょうか？\u0002"
    ],
    "Translation": ""
  },
  {
    "Text": [
      "住民投票の日がいよいよ\u0001",
      "３日後に迫りましたわね。\u0002"
    ],
    "Translation": ""
  },
  {
    "Text": [
      "結果は目に見えていますが、\u0001",
      "当日はわたくしも\u0001",
      "投票に行く予定でいますわ。\u0002"
    ],
    "Translation": ""
  },
  {
    "Text": [
      "どちらかに投票するかは……\u0001",
      "一応秘密にさせてくださいな。\u0002"
    ],
    "Translation": ""
  },
  {
    "Text": [
      "結果は目に見えていますが、\u0001",
      "当日はわたくしも\u0001",
      "投票に行く予定でいますわ。\u0002"
    ],
    "Translation": ""
  },
  {
    "Text": [
      "どちらかに投票するかは……\u0001",
      "一応秘密にさせてくださいな。\u0002"
    ],
    "Translation": ""
  },
  {
    "Text": [
      "ドレイク・オーナー、\u0001",
      "今日は何だか少し眠たそうですわね。\u0002"
    ],
    "Translation": ""
  },
  {
    "Text": [
      "また遅くまで\u0001",
      "飲んでいらしたのでしょうか？\u0002"
    ],
    "Translation": ""
  },
  {
    "Text": [
      "こんな雨の日はどうぞ当店で\u0001",
      "愉しんで行って下さいませ。\u0002"
    ],
    "Translation": ""
  },
  {
    "Text": [
      "うふふ、もしかしたら\u0001",
      "サービスするかもしれませんよ？\u0002"
    ],
    "Translation": ""
  },
  {
    "Text": [
      "ギャンブルでも何でも……\u0001",
      "重要なのは引き際ですわ。\u0002"
    ],
    "Translation": ""
  },
  {
    "Text": [
      "分相応という言葉もありますし、\u0001",
      "多くを望むと大概失敗しますわよ？\u0002"
    ],
    "Translation": ""
  },
  {
    "Text": [
      "わたくし、人間はスリルを\u0001",
      "求める生き物だと思いますの。\u0002"
    ],
    "Translation": ""
  },
  {
    "Text": [
      "お客様も一勝負どうかしら。\u0001",
      "極上のスリルを\u0001",
      "プレゼントいたしますわよ？\u0002"
    ],
    "Translation": ""
  },
  {
    "Text": "クロスベルが独立すべきか否か……\u0002",
    "Translation": ""
  },
  {
    "Text": [
      "まったく、ディーター市長は\u0001",
      "とんでもない難題をわたくしたちに\u0001",
      "突きつけてくれたものですわね。\u0002"
    ],
    "Translation": ""
  },
  {
    "Text": [
      "うふふ、いよいよ本会議の\u0001",
      "当日がやって来ましたわね。\u0002"
    ],
    "Translation": ""
  },
  {
    "Text": [
      "今から次のクロスベルタイムズが\u0001",
      "愉しみで仕方ありませんわ。\u0002"
    ],
    "Translation": ""
  },
  {
    "Text": [
      "わたくしまだ見ていないのですが、\u0001",
      "オルキスタワーは、それはそれは\u0001",
      "立派なビルだそうですね。\u0002"
    ],
    "Translation": ""
  },
  {
    "Text": [
      "地上４０階の超高層ビルディング……\u0001",
      "目に焼き付けるのが楽しみですわ。\u0002"
    ],
    "Translation": ""
  },
  {
    "Text": [
      "ディーター市長の呼びかけた\u0001",
      "国際会議がいよいよ始まりますわね。\u0002"
    ],
    "Translation": ""
  },
  {
    "Text": [
      "互いの真理を読み合い、\u0001",
      "それぞれが持つ様々な切り札",
      "#6Rカード#",
      "を\u0001",
      "ここぞというタイミングで切る……\u0002"
    ],
    "Translation": ""
  },
  {
    "Text": [
      "こう言っては何ですけど、\u0001",
      "わたくし外交もギャンブルも\u0001",
      "本質は同じだと思いますわ。\u0002"
    ],
    "Translation": ""
  },
  {
    "Text": [
      "今回の場を設けるにあたり、\u0001",
      "ディーター市長は\u0001",
      "いかなる切り札",
      "#6Rカード#",
      "を用意したのか……\u0002"
    ],
    "Translation": ""
  },
  {
    "Text": "うふふ、興味が尽きませんわね。\u0002",
    "Translation": ""
  },
  {
    "Text": "ふふ、お客様も一勝負いかがですか？\u0002",
    "Translation": ""
  },
  {
    "Text": "思考の迷宮に、ご招待致しますわよ。\u0002",
    "Translation": ""
  },
  {
    "Text": [
      "カジノハウス《バルカ》へようこそ。\u0001",
      "こちらではルーレットが楽しめますわ。\u0002"
    ],
    "Translation": ""
  },
  {
    "Text": [
      "はじめにお断りしておきますが、\u0001",
      "この台にイカサマの類を\u0001",
      "仕掛けることは一切不可能……\u0002"
    ],
    "Translation": ""
  },
  {
    "Text": [
      "どうです、一度小細工なしに\u0001",
      "運命に身を委ねてみませんか？\u0002"
    ],
    "Translation": ""
  },
  {
    "Text": [
      "広く薄く堅実に張るも良し……\u0001",
      "狭く厚く勝負に出るも良し……\u0002"
    ],
    "Translation": ""
  },
  {
    "Text": "全ての結果は女神のみぞ知る、ですわ。\u0002",
    "Translation": ""
  },
  {
    "Text": [
      "私は丁度いなかったんだけど、\u0001",
      "１週間前にとんでもない事件が\u0001",
      "起こったそうね。\u0002"
    ],
    "Translation": ""
  },
  {
    "Text": [
      "今後も同じような事がないとは\u0001",
      "言い切れないみたいだし……\u0002"
    ],
    "Translation": ""
  },
  {
    "Text": [
      "クロスベルに遊びに来るのも\u0001",
      "そろそろ控えた方がいいかもね。\u0002"
    ],
    "Translation": ""
  },
  {
    "Text": [
      "今後も同じような事がないとは\u0001",
      "言い切れないみたいだし……\u0002"
    ],
    "Translation": ""
  },
  {
    "Text": [
      "クロスベルに遊びに来るのも\u0001",
      "そろそろ控えた方がいいかもね。\u0002"
    ],
    "Translation": ""
  },
  {
    "Text": [
      "謎の武装集団の目的って\u0001",
      "一体何なのかしら……？\u0002"
    ],
    "Translation": ""
  },
  {
    "Text": [
      "今後どんな要求が\u0001",
      "どこから出てくるかで自ずと\u0001",
      "分かって来るんでしょうけど……\u0002"
    ],
    "Translation": ""
  },
  {
    "Text": [
      "そういえば今日は、\u0001",
      "市民会館の方で市民フォーラムを\u0001",
      "やってるって話ね。\u0002"
    ],
    "Translation": ""
  },
  {
    "Text": [
      "社会見学のつもりで、\u0001",
      "後でちょっと見てこようかしら？\u0002"
    ],
    "Translation": ""
  },
  {
    "Text": [
      "ふう、クロスベルで遊ぶのにも\u0001",
      "また飽きてきちゃったわね。\u0002"
    ],
    "Translation": ""
  },
  {
    "Text": "何か面白い事はないかしら？\u0002",
    "Translation": ""
  },
  {
    "Text": [
      "昨日のドラ息子たち、\u0001",
      "最初は調子よかったんだけど\u0001",
      "結局最後には大負けしてたの。\u0002"
    ],
    "Translation": ""
  },
  {
    "Text": [
      "よっぽど悔しかったのか、\u0001",
      "汚い捨てゼリフを吐いて\u0001",
      "さっさと帰っていったけど……\u0002"
    ],
    "Translation": ""
  },
  {
    "Text": [
      "うふふ、あんな人たちには\u0001",
      "女神も愛想を尽かすわよね。\u0002"
    ],
    "Translation": ""
  },
  {
    "Text": [
      "昨日のドラ息子たち、\u0001",
      "今日はカジノに来てないみたい。\u0002"
    ],
    "Translation": ""
  },
  {
    "Text": [
      "うふふ、今日はゲームに\u0001",
      "集中できそうね。\u0002"
    ],
    "Translation": ""
  },
  {
    "Text": [
      "私、親のミラと権力にべったりの\u0001",
      "底の浅い男なんかに興味は無いわ。\u0002"
    ],
    "Translation": ""
  },
  {
    "Text": [
      "うふふ、やっぱり\u0001",
      "ドレイク・オーナーみたいに\u0001",
      "渋くてダンディじゃないとね。\u0002"
    ],
    "Translation": ""
  },
  {
    "Text": [
      "いくらミラをもってようが、\u0001",
      "ドラ息子なんかお断りだわ。\u0002"
    ],
    "Translation": ""
  },
  {
    "Text": [
      "うふふ、やっぱり\u0001",
      "ドレイク・オーナーみたいに\u0001",
      "渋くてダンディじゃないとね。\u0002"
    ],
    "Translation": ""
  },
  {
    "Text": [
      "通商会議か……\u0001",
      "ふふ、ディーター市長って\u0001",
      "本当にやり手よね。\u0002"
    ],
    "Translation": ""
  },
  {
    "Text": [
      "これだけの政治手腕……\u0001",
      "ギャンブルの方もお強いのかしら？\u0002"
    ],
    "Translation": ""
  },
  {
    "Text": [
      "ガレッティさん、\u0001",
      "以前ガンツさんに負けたのを\u0001",
      "まだ根に持っているみたいなの。\u0002"
    ],
    "Translation": ""
  },
  {
    "Text": [
      "ふふ、勝負師ってのは\u0001",
      "本当に負けず嫌いばかりよね。\u0002"
    ],
    "Translation": ""
  },
  {
    "Text": [
      "あら、貴方ランディじゃない。\u0001",
      "お久しぶりね。\u0002"
    ],
    "Translation": ""
  },
  {
    "Text": [
      "#00305F",
      "おお、そういうアンタは\u0001",
      "レイタロッサのお姉さん。\u0002",
      "\u0003",
      "#00302F",
      "どうだい、再会を祝して\u0001",
      "今度俺とデートでも……\u0002"
    ],
    "Translation": ""
  },
  {
    "Text": [
      "ふふ、そうね。\u0001",
      "私との勝負に勝てたら\u0001",
      "考えてあげてもいいわよ？\u0002"
    ],
    "Translation": ""
  },
  {
    "Text": [
      "#00309F",
      "おお、言ったな？\u0001",
      "ならさっそく――\u0002"
    ],
    "Translation": ""
  },
  {
    "Text": [
      "#00009F",
      "なあ、ランディ。\u0002"
    ],
    "Translation": ""
  },
  {
    "Text": [
      "#00109F",
      "ふふ、もちろん冗談よね？\u0002"
    ],
    "Translation": ""
  },
  {
    "Text": [
      "#00306F",
      "あ、ああ……\u0001",
      "ってか笑顔が怖ぇぞ、２人とも。\u0002"
    ],
    "Translation": ""
  },
  {
    "Text": [
      "#00109F",
      "ねえ、ランディ。\u0001",
      "さっきも言ったと思うけど……\u0002"
    ],
    "Translation": ""
  },
  {
    "Text": [
      "#00306F",
      "あ、ああ……\u0001",
      "だから冗談だって。\u0002"
    ],
    "Translation": ""
  },
  {
    "Text": [
      "#10106F",
      "（ランディ先輩……\u0001",
      "  本当に懲りないですね。）\u0002"
    ],
    "Translation": ""
  },
  {
    "Text": [
      "ふふ、どうやら\u0001",
      "勝負はお預けみたいね。\u0002"
    ],
    "Translation": ""
  },
  {
    "Text": [
      "といっても、\u0001",
      "次があるかどうかは\u0001",
      "分からないけど。\u0002"
    ],
    "Translation": ""
  },
  {
    "Text": [
      "#00306F",
      "くぅ～、そりゃねえぜ。\u0002"
    ],
    "Translation": ""
  },
  {
    "Text": [
      "ふふ、どうやら\u0001",
      "勝負はお預けみたいね。\u0002"
    ],
    "Translation": ""
  },
  {
    "Text": [
      "といっても、\u0001",
      "次があるかどうかは\u0001",
      "分からないけど。\u0002"
    ],
    "Translation": ""
  },
  {
    "Text": "あ～あ、また負けちゃったわ。\u0002",
    "Translation": ""
  },
  {
    "Text": [
      "ふふ、でも\u0001",
      "これで終わる私じゃないわよ。\u0002"
    ],
    "Translation": ""
  },
  {
    "Text": [
      "しばらくクロスベルに\u0001",
      "来るのは控えてたんだけど……\u0001",
      "結局また来ちゃったわ。\u0002"
    ],
    "Translation": ""
  },
  {
    "Text": [
      "故郷カルバードも悪くないけど、\u0001",
      "やっぱりクロスベルの空気は格別よね。\u0002"
    ],
    "Translation": ""
  },
  {
    "Text": [
      "くう、異変が収まってそのまま\u0001",
      "スロットで遊んでおったら、\u0001",
      "婆さんが乗り込んできおった。\u0002"
    ],
    "Translation": ""
  },
  {
    "Text": "……さすがに心配をかけたかのう。\u0002",
    "Translation": ""
  },
  {
    "Text": [
      "戒厳令など大したことないと\u0001",
      "タカをくくって、\u0001",
      "遊びにきていたんじゃが……\u0002"
    ],
    "Translation": ""
  },
  {
    "Text": [
      "ま、まさかこんな事に\u0001",
      "巻き込まれてしまうとは……\u0001",
      "一生の不覚じゃわい。\u0002"
    ],
    "Translation": ""
  },
  {
    "Text": [
      "今頃、婆さんも\u0001",
      "心配しとるじゃろうな……\u0002"
    ],
    "Translation": ""
  },
  {
    "Text": [
      "こんな事に\u0001",
      "巻き込まれてしまうとは……\u0001",
      "一生の不覚じゃわい。\u0002"
    ],
    "Translation": ""
  },
  {
    "Text": [
      "今頃、婆さんも\u0001",
      "心配しとるじゃろうな……\u0002"
    ],
    "Translation": ""
  },
  {
    "Text": [
      "さっき演説を聞いてきたが……\u0001",
      "凄い話になったものじゃのう。\u0002"
    ],
    "Translation": ""
  },
  {
    "Text": [
      "正直、わしには\u0001",
      "何が正しいのか分からんよ。\u0002"
    ],
    "Translation": ""
  },
  {
    "Text": [
      "１週間前の襲撃事件には、\u0001",
      "本当に恐怖を味わわされたのう。\u0002"
    ],
    "Translation": ""
  },
  {
    "Text": [
      "じゃが、わしはこういう時こそ\u0001",
      "元気を出さねばいかんと思うのじゃ。\u0002"
    ],
    "Translation": ""
  },
  {
    "Text": [
      "どうやら、マインツで\u0001",
      "大変な事が起こっとるようじゃな。\u0002"
    ],
    "Translation": ""
  },
  {
    "Text": [
      "家におっても何となく\u0001",
      "落ち着かんから出てきたが……\u0001",
      "今日は流石に気乗りがせんわい。\u0002"
    ],
    "Translation": ""
  },
  {
    "Text": [
      "婆さんにも悪いし、\u0001",
      "さっさと帰るとするかのう。\u0002"
    ],
    "Translation": ""
  },
  {
    "Text": [
      "家におっても何となく\u0001",
      "落ち着かんから出てきたが……\u0001",
      "今日は流石に気乗りがせんわい。\u0002"
    ],
    "Translation": ""
  },
  {
    "Text": [
      "婆さんにも悪いし、\u0001",
      "さっさと帰るとするかのう。\u0002"
    ],
    "Translation": ""
  },
  {
    "Text": [
      "昨日は負けに負けてしもうての……\u0001",
      "今日は必ず取り返すつもりじゃよ。\u0002"
    ],
    "Translation": ""
  },
  {
    "Text": "今に見ておれぇ、わしはやるぞぉお！\u0002",
    "Translation": ""
  },
  {
    "Text": [
      "おおっ！？　今のは当たりでは……\u0001",
      "……ってなんじゃ、肩透かしか。\u0002"
    ],
    "Translation": ""
  },
  {
    "Text": [
      "くぬうううぅ……\u0001",
      "なぜ来ん、なぜ来んのじゃ！\u0002"
    ],
    "Translation": ""
  },
  {
    "Text": [
      "#00304F",
      "（やれやれ、爺さん\u0001",
      "  また熱くなってんな。）\u0002"
    ],
    "Translation": ""
  },
  {
    "Text": [
      "くぬうううぅ……\u0001",
      "なぜ来ん、なぜ来んのじゃ！\u0002"
    ],
    "Translation": ""
  },
  {
    "Text": "わしは百戦錬磨の勝負師じゃぞ！\u0002",
    "Translation": ""
  },
  {
    "Text": [
      "ふむむ、今日は\u0001",
      "いまいち当たりが来んのう。\u0002"
    ],
    "Translation": ""
  },
  {
    "Text": [
      "こんな体たらくで帰っては\u0001",
      "婆さんに何と言われるか……\u0002"
    ],
    "Translation": ""
  },
  {
    "Text": [
      "ええい、出ろッ！\u0001",
      "出んかッ、出てこいやッ！\u0002"
    ],
    "Translation": ""
  },
  {
    "Text": [
      "ふむむ……\u0001",
      "こんな体たらくで帰っては\u0001",
      "婆さんに何と言われるか……\u0002"
    ],
    "Translation": ""
  },
  {
    "Text": [
      "ええい、出ろッ！\u0001",
      "出なさいッ、出てきてちょッ！\u0002"
    ],
    "Translation": ""
  },
  {
    "Text": [
      "クロスベルの独立には、\u0001",
      "わしは全面的に賛成じゃ。\u0002"
    ],
    "Translation": ""
  },
  {
    "Text": [
      "そもそも税収の一部を\u0001",
      "２大国に納めるという話が\u0001",
      "ナンセンスじゃからのう。\u0002"
    ],
    "Translation": ""
  },
  {
    "Text": "独立は当然の権利じゃよ。\u0002",
    "Translation": ""
  },
  {
    "Text": [
      "そもそも、税収の一部を\u0001",
      "２大国に納めるという話が\u0001",
      "ナンセンスじゃからのう。\u0002"
    ],
    "Translation": ""
  },
  {
    "Text": "独立は当然の権利じゃよ。\u0002",
    "Translation": ""
  },
  {
    "Text": [
      "今朝は婆さんが\u0001",
      "不敵に笑っておってな。\u0002"
    ],
    "Translation": ""
  },
  {
    "Text": [
      "なぜ笑うのかと問うたら、\u0001",
      "じきに分かると言っておったが……\u0002"
    ],
    "Translation": ""
  },
  {
    "Text": [
      "どうやら、婆さんに\u0001",
      "いつの間にか財布の中身を\u0001",
      "抜かれておったみたいなんじゃ。\u0002"
    ],
    "Translation": ""
  },
  {
    "Text": [
      "#00305F",
      "ん？　じゃあリッケ爺さん、\u0001",
      "ミラもなしに何してんだ？\u0002"
    ],
    "Translation": ""
  },
  {
    "Text": "……ただ座っとるだけじゃ、悪いか？\u0002",
    "Translation": ""
  },
  {
    "Text": [
      "#00306F",
      "いや……まあ混んでる\u0001",
      "ワケでもねえし、悪くはねえがよ。\u0002"
    ],
    "Translation": ""
  },
  {
    "Text": [
      "ミラがない以上、遊べんが……\u0001",
      "わしは絶対に家へは帰らんぞ。\u0002"
    ],
    "Translation": ""
  },
  {
    "Text": [
      "ここで屈してしまっては、\u0001",
      "婆さんの思うツボじゃからな。\u0002"
    ],
    "Translation": ""
  },
  {
    "Text": [
      "世間が除幕式で騒ごうが、\u0001",
      "わしはとにかくここで\u0001",
      "スロットを打つだけじゃい。\u0002"
    ],
    "Translation": ""
  },
  {
    "Text": [
      "婆さんは婆さんで、茶飲み仲間と\u0001",
      "ヨロシクやっとるからのう。\u0002"
    ],
    "Translation": ""
  },
  {
    "Text": [
      "#00300F",
      "よう、リッケ爺さん。\u0001",
      "元気にしてたかい？\u0002"
    ],
    "Translation": ""
  },
  {
    "Text": [
      "ほほ、その声はランディか。\u0001",
      "久しぶりじゃのう。\u0002"
    ],
    "Translation": ""
  },
  {
    "Text": [
      "見ての通り元気も元気、\u0001",
      "大フィーバーじゃ！\u0002"
    ],
    "Translation": ""
  },
  {
    "Text": "分かったら邪魔せんでくれ！\u0002",
    "Translation": ""
  },
  {
    "Text": [
      "#00300F",
      "はは、そいつはすまねえな。\u0002"
    ],
    "Translation": ""
  },
  {
    "Text": "今いい所なんじゃ、邪魔せんでくれ！\u0002",
    "Translation": ""
  },
  {
    "Text": "……おおっ、また来よったぞ！\u0002",
    "Translation": ""
  },
  {
    "Text": [
      "婆さんが何と言おうと、\u0001",
      "わしはギャンブルを\u0001",
      "止めるつもりは一切ないぞ。\u0002"
    ],
    "Translation": ""
  },
  {
    "Text": [
      "これも勝負師に生まれついた\u0001",
      "定めというヤツじゃ、ほっほっほ。\u0002"
    ],
    "Translation": ""
  },
  {
    "Text": [
      "ほっほっ、今日も\u0001",
      "スロットがよう出よるのう。\u0002"
    ],
    "Translation": ""
  },
  {
    "Text": [
      "メダルのじゃらじゃらする\u0001",
      "音がたまらん心地じゃわい。\u0002"
    ],
    "Translation": ""
  },
  {
    "Text": [
      "ほんと、あなたって人は……\u0001",
      "どうして家に帰ってこないの！\u0002"
    ],
    "Translation": ""
  },
  {
    "Text": "さあ、早く帰りますよ！\u0002",
    "Translation": ""
  },
  {
    "Text": [
      "ま、待ってくれ婆さん。\u0001",
      "せめてこのコインを交換してから……\u0002"
    ],
    "Translation": ""
  },
  {
    "Text": "ええい、お黙りなさいっ！！\u0002",
    "Translation": ""
  },
  {
    "Text": "そんな、後生じゃ～！！\u0002",
    "Translation": ""
  },
  {
    "Text": [
      "#00300F",
      "よう、リッケ爺さん。\u0001",
      "調子はどうよ。\u0002"
    ],
    "Translation": ""
  },
  {
    "Text": "あん？　その声はランディ？\u0002",
    "Translation": ""
  },
  {
    "Text": "最近、顔を出さないじゃないか。\u0002",
    "Translation": ""
  },
  {
    "Text": [
      "#00306F",
      "ま、ちょっと仕事が忙しくてな。\u0002"
    ],
    "Translation": ""
  },
  {
    "Text": [
      "忙しいからこそ遊ぶのじゃ。\u0001",
      "分かっておらんのう。\u0002"
    ],
    "Translation": ""
  },
  {
    "Text": [
      "#00300F",
      "はは、確かにそうかもな。\u0002"
    ],
    "Translation": ""
  },
  {
    "Text": [
      "婆さんめ、今朝は\u0001",
      "玄関先で待ち伏せしておったよ。\u0002"
    ],
    "Translation": ""
  },
  {
    "Text": "眉を吊り上げて一喝しおってな。\u0002",
    "Translation": ""
  },
  {
    "Text": [
      "危なく連れ戻される所じゃった。\u0001",
      "ふう、まさに間一髪じゃよ。\u0002"
    ],
    "Translation": ""
  },
  {
    "Text": [
      "クロスベルがいかに変わろうとも\u0001",
      "歓楽街だけは無くならんじゃろう。\u0002"
    ],
    "Translation": ""
  },
  {
    "Text": [
      "バーに賭博場、溢れる観光客に\u0001",
      "群がるギャルたち㈱\u0002"
    ],
    "Translation": ""
  },
  {
    "Text": [
      "姿かたちは変化しようとも\u0001",
      "昔から何一つ変わっておらんよ。\u0002"
    ],
    "Translation": ""
  },
  {
    "Text": [
      "……ついでにちーっとばかり\u0001",
      "治安が悪い所もな。\u0001",
      "素人は気を付けることじゃ。\u0002"
    ],
    "Translation": ""
  },
  {
    "Text": [
      "まったく、この人ったら……\u0001",
      "私がどれだけ心配したと\u0001",
      "思っているのかしら。\u0002"
    ],
    "Translation": ""
  },
  {
    "Text": "……当分はお小遣いゼロね。\u0002",
    "Translation": ""
  },
  {
    "Text": [
      "う～ん、赤・赤とくれば\u0001",
      "次は黒だと思ったんだけどな……\u0002"
    ],
    "Translation": ""
  },
  {
    "Text": [
      "ふう、ギャンブルってのは\u0001",
      "一筋縄ではいかないものだね。\u0002"
    ],
    "Translation": ""
  },
  {
    "Text": [
      "気晴らしにいいと思って、\u0001",
      "ガンツの付き合いで来てたんだが……\u0002"
    ],
    "Translation": ""
  },
  {
    "Text": [
      "早めに帰って、今後について\u0001",
      "町長たちと相談したほうが良さそうだな。\u0002"
    ],
    "Translation": ""
  },
  {
    "Text": [
      "はは、だからあの時\u0001",
      "やめときゃ良かったんだ。\u0002"
    ],
    "Translation": ""
  },
  {
    "Text": [
      "ガンツ、お前は\u0001",
      "欲張りすぎなんだよ。\u0002"
    ],
    "Translation": ""
  },
  {
    "Text": [
      "クロスベル市に来てみたら\u0001",
      "こんな大変なことに\u0001",
      "なっちまってるとはな……\u0002"
    ],
    "Translation": ""
  },
  {
    "Text": [
      "……はあ、せっかくのカジノなのに\u0001",
      "気分が乗らねえよ。\u0002"
    ],
    "Translation": ""
  },
  {
    "Text": [
      "ああ、くそ……！\u0001",
      "せっかく勝ってたのに\u0001",
      "もうパーじゃねえかっ！\u0002"
    ],
    "Translation": ""
  },
  {
    "Text": [
      "独立の是非がどうとか\u0001",
      "世間では騒がれているようだが……\u0001",
      "まったく愚かな奴ばかりだ。\u0002"
    ],
    "Translation": ""
  },
  {
    "Text": [
      "クロスベルは今までどおり\u0001",
      "共和国に媚びへつらい、\u0001",
      "従っていればいいんだよ。\u0002"
    ],
    "Translation": ""
  },
  {
    "Text": [
      "そうしている間は\u0001",
      "平和が約束されるだろうしな。\u0001",
      "ククク……\u0002"
    ],
    "Translation": ""
  },
  {
    "Text": [
      "まあ、独立しようがしまいが\u0001",
      "俺たちには関係ないがな。\u0002"
    ],
    "Translation": ""
  },
  {
    "Text": [
      "クク、せいぜいこの街で\u0001",
      "遊び尽くさせてもらうだけさ。\u0002"
    ],
    "Translation": ""
  },
  {
    "Text": "ククッ、ほどほどにしとけよユーリ～。\u0002",
    "Translation": ""
  },
  {
    "Text": [
      "あんまり勝ちすぎると、\u0001",
      "出禁食らっちまうかもしれねえぜ～？\u0002"
    ],
    "Translation": ""
  },
  {
    "Text": [
      "あっちに座ってる女、\u0001",
      "なかなかの美人なんだけどな～。\u0002"
    ],
    "Translation": ""
  },
  {
    "Text": [
      "俺たちの誘いを断るなんて\u0001",
      "見る目がないっつーの。\u0002"
    ],
    "Translation": ""
  },
  {
    "Text": [
      "#03500F",
      "さて、俺ももうちょいしたら\u0001",
      "帝国に帰るとするかね。\u0002",
      "\u0003",
      "#03504F",
      "あのチョイ悪ヒゲオヤジも\u0001",
      "助けてやんねえといけねえし……\u0001",
      "やれやれ、頼れる男はツラいぜェ。\u0002"
    ],
    "Translation": ""
  },
  {
    "Text": [
      "#03500F",
      "さて、俺ももうちょいしたら\u0001",
      "帝国に帰るとするかね。\u0002",
      "\u0003",
      "#03504F",
      "やれやれ、頼れる男はツラいぜェ。\u0002"
    ],
    "Translation": ""
  },
  {
    "Text": [
      "#11P",
      "#03502F",
      "よぉ、お疲れさん。\u0002"
    ],
    "Translation": ""
  },
  {
    "Text": [
      "#6P",
      "#00006F",
      "レ、レクターさん……\u0001",
      "またそんな格好でカジノに……\u0002"
    ],
    "Translation": ""
  },
  {
    "Text": [
      "#10402F",
      "フフ、ものすごく寛いでるね。\u0002"
    ],
    "Translation": ""
  },
  {
    "Text": [
      "#10106F",
      "ものすごく寛いでますね……\u0002"
    ],
    "Translation": ""
  },
  {
    "Text": [
      "#10702F",
      "ものすごく寛いでる\u0001",
      "みたいですね……\u0002"
    ],
    "Translation": ""
  },
  {
    "Text": [
      "#6P",
      "#00205F",
      "書記官の服は\u0001",
      "どうされたんですか？\u0002"
    ],
    "Translation": ""
  },
  {
    "Text": [
      "#11P",
      "#03506F",
      "ああ、《魔導兵》との戦闘中に\u0001",
      "ビリっと破けちまってなァ。\u0002",
      "\u0003",
      "#03509F",
      "まあ、気にせず楽にしてくれたまへ。\u0002"
    ],
    "Translation": ""
  },
  {
    "Text": [
      "#6P",
      "#00006F",
      "は、はあ……\u0002",
      "\u0003",
      "#00000F",
      "コホン、えっと……\u0001",
      "解放作戦へのご協力、\u0001",
      "ありがとうございました。\u0002"
    ],
    "Translation": ""
  },
  {
    "Text": [
      "#00104F",
      "オルキスタワーの突入では\u0001",
      "本当にお世話になってしまって……\u0002"
    ],
    "Translation": ""
  },
  {
    "Text": [
      "#11P",
      "#03504F",
      "ハハ、いいってことよ。\u0001",
      "こっちも好きでやったことだしな。\u0002",
      "\u0003",
      "#03502F",
      "書記官としての\u0001",
      "デスクワークばっかだったから、\u0001",
      "正直いい運動になったぜ。\u0002"
    ],
    "Translation": ""
  },
  {
    "Text": [
      "#12P",
      "#00306F",
      "アンタの仕事は諜報員だろうが……\u0001",
      "あんだけ動き回っといてよく言うぜ。\u0002",
      "\u0003",
      "#00301F",
      "しかし、キリカさんはともかく\u0001",
      "あんたがあそこまでの\u0001",
      "戦闘力を隠し持ってたとはな。\u0002",
      "\u0003",
      "あの剣術と高位アーツ……\u0001",
      "素人が一朝一夕で\u0001",
      "扱えるもんじゃねえはずだ。\u0002"
    ],
    "Translation": ""
  },
  {
    "Text": [
      "#11P",
      "#03510F",
      "ふむ、そんなに\u0001",
      "知りたいなら教えてしんぜよう。\u0002",
      "\u0003",
      "#03504F",
      "そう、あれは約３０年前……\u0001",
      "帝国のとある山奥に住む\u0001",
      "仙人に教わったものでな。\u0002"
    ],
    "Translation": ""
  },
  {
    "Text": [
      "#6P",
      "#00006F",
      "……出だしからあからさまに\u0001",
      "ウソ臭いんですが。\u0002"
    ],
    "Translation": ""
  },
  {
    "Text": [
      "#00603F",
      "（やれやれ……食えん男だ。）\u0002"
    ],
    "Translation": ""
  },
  {
    "Text": [
      "#10106F",
      "さすがに適当すぎますね……\u0002"
    ],
    "Translation": ""
  },
  {
    "Text": [
      "#10409F",
      "アハハ、適当極まりないね。\u0002"
    ],
    "Translation": ""
  },
  {
    "Text": [
      "#11P",
      "#03504F",
      "ま、その辺は\u0001",
      "お好きに想像してくれってな。\u0002",
      "\u0003",
      "#03510F",
      "……さて、俺もそろそろ\u0001",
      "帝国に帰んないといけねえなあ。\u0002",
      "\u0003",
      "#03506F",
      "あのチョイ悪ヒゲオヤジも\u0001",
      "助けてやんねえといけねえし。\u0002"
    ],
    "Translation": ""
  },
  {
    "Text": [
      "#6P",
      "#00205F",
      "《鉄血宰相》……\u0001",
      "確か、撃たれて行方不明に\u0001",
      "なっているんでしたよね。\u0002",
      "\u0003",
      "#00203F",
      "《神機》によって\u0001",
      "正規軍が大打撃を受けたスキを\u0001",
      "貴族勢力に突かれたとか……\u0002"
    ],
    "Translation": ""
  },
  {
    "Text": [
      "#11P",
      "#03510F",
      "ああ、帝都もすっかり\u0001",
      "貴族どもに占領されちまったそうだ。\u0002",
      "\u0003",
      "#03506F",
      "やれやれ、それにしても\u0001",
      "逆恨みされやすいオッサンだよなァ。\u0001",
      "お守りする俺らの身にもなれっての。\u0002",
      "\u0003",
      "#03500F",
      "ま、あのオッサンのことだから\u0001",
      "簡単にくたばりゃしねえだろうがな。\u0002"
    ],
    "Translation": ""
  },
  {
    "Text": [
      "#12P",
      "#00302F",
      "なんだか気楽だなあ……\u0002"
    ],
    "Translation": ""
  },
  {
    "Text": [
      "#11P",
      "#03509F",
      "ハハ、あんたらこそどうなのよ？\u0002",
      "\u0003",
      "#03504F",
      "ギリアスのオッサンと貴族勢力、\u0001",
      "どちらが勝ったとしても……\u0002",
      "\u0003",
      "#03502F",
      "この先、クロスベルの運命は\u0001",
      "変わらないと思うけどなァ。\u0002"
    ],
    "Translation": ""
  },
  {
    "Text": [
      "#00108F",
      "……それは……\u0002"
    ],
    "Translation": ""
  },
  {
    "Text": [
      "#6P",
      "#00003F",
      "……この先、どうしていくかは\u0001",
      "まだ分かりません。\u0002",
      "\u0003",
      "#00001F",
      "ですが、何はなくとも……\u0001",
      "まずはキーアを取り戻すため、\u0001",
      "あの《大樹》に向かうつもりです。\u0002"
    ],
    "Translation": ""
  },
  {
    "Text": [
      "#11P",
      "#03504F",
      "……ハハ、それでいい。\u0002",
      "\u0003",
      "先を見据えるのは大事だが、\u0001",
      "そればっかりに捉われちゃ\u0001",
      "足元をすくわれる。\u0002",
      "\u0003",
      "#03500F",
      "何より大事なのは\u0001",
      "目の前にある“今”だからな。\u0002"
    ],
    "Translation": ""
  },
  {
    "Text": [
      "#6P",
      "#00006F",
      "きゅ、急にまともな事を言われても\u0001",
      "それはそれで戸惑うんですが……\u0002",
      "\u0003",
      "#00000F",
      "……ありがとうございます。\u0002"
    ],
    "Translation": ""
  },
  {
    "Text": [
      "#11P",
      "#03502F",
      "ハハ、まあせいぜい\u0001",
      "足掻いてみろってこった。\u0002",
      "\u0003",
      "#03509F",
      "そうでなくちゃあ、\u0001",
      "俺もわざわざ居残りまでした\u0001",
      "甲斐がねえからなァ。\u0002"
    ],
    "Translation": ""
  },
  {
    "Text": [
      "スロットで遊ぶ\u0001",
      "やめる\u0001"
    ],
    "Translation": ""
  },
  {
    "Text": [
      "#5P",
      "これは皆さん。\u0002"
    ],
    "Translation": ""
  },
  {
    "Text": [
      "#5P",
      "……もしやランディの件で\u0001",
      "いらっしゃったんですか？\u0002"
    ],
    "Translation": ""
  },
  {
    "Text": [
      "#12P",
      "#00001F",
      "はい……\u0001",
      "やはり彼はこちらに？\u0002"
    ],
    "Translation": ""
  },
  {
    "Text": [
      "#5P",
      "ええ、夜中の３時くらいに\u0001",
      "店にフラリと現れまして……\u0002"
    ],
    "Translation": ""
  },
  {
    "Text": [
      "#5P",
      "しばらくここで飲んでから\u0001",
      "帰って行きましたが……\u0002"
    ],
    "Translation": ""
  },
  {
    "Text": [
      "#12P",
      "#00206F",
      "……どうやら真っ先に\u0001",
      "こちらを訪れたみたいですね。\u0002"
    ],
    "Translation": ""
  },
  {
    "Text": [
      "#10301F",
      "#12P",
      "それで、その後どこかに\u0001",
      "行くとか言ってなかったかい？\u0002"
    ],
    "Translation": ""
  },
  {
    "Text": [
      "#5P",
      "……やはり支援課には\u0001",
      "戻らなかったみたいですね。\u0002"
    ],
    "Translation": ""
  },
  {
    "Text": [
      "#5P",
      "いえ、どこに行くとは\u0001",
      "特に言っていませんでした。\u0002"
    ],
    "Translation": ""
  },
  {
    "Text": [
      "#5P",
      "ただ、どうも飲んでいる最中、\u0001",
      "いつも以上に減らず口が多くて……\u0002"
    ],
    "Translation": ""
  },
  {
    "Text": [
      "#5P",
      "おまけに帰り際、ある物を\u0001",
      "私から引き取って行ったんです。\u0002"
    ],
    "Translation": ""
  },
  {
    "Text": [
      "#12P",
      "#00005F",
      "ある物……ですか？\u0002"
    ],
    "Translation": ""
  },
  {
    "Text": [
      "#5P",
      "ええ……随分重いトランクで\u0001",
      "中身は私も存じません。\u0002"
    ],
    "Translation": ""
  },
  {
    "Text": [
      "#5P",
      "２年前、ランディがこの街に\u0001",
      "来たばかりの時に預かったんです。\u0002"
    ],
    "Translation": ""
  },
  {
    "Text": [
      "#5P",
      "『俺が死んだらジャンク屋あたりに\u0001",
      "  バラして売り払ってくれ』と言って。\u0002"
    ],
    "Translation": ""
  },
  {
    "Text": [
      "#00106F",
      "そんな……\u0002"
    ],
    "Translation": ""
  },
  {
    "Text": [
      "#12P",
      "#10108F",
      "……ランディ先輩……\u0002"
    ],
    "Translation": ""
  },
  {
    "Text": [
      "#6P",
      "#00206F",
      "……らしく無さすぎです。\u0002"
    ],
    "Translation": ""
  },
  {
    "Text": [
      "#5P",
      "#00008F",
      "……………………………………\u0002"
    ],
    "Translation": ""
  },
  {
    "Text": [
      "#5P",
      "……ヤツの経歴については\u0001",
      "私もある程度は存じています。\u0002"
    ],
    "Translation": ""
  },
  {
    "Text": [
      "#5P",
      "ですが、過去にどんな事が\u0001",
      "あったのかまでは知りません。\u0002"
    ],
    "Translation": ""
  },
  {
    "Text": [
      "#5P",
      "それを知ってヤツの力になれるのは\u0001",
      "恐らく、皆さんだけでしょう。\u0002"
    ],
    "Translation": ""
  },
  {
    "Text": [
      "#00100F",
      "オーナー……\u0002"
    ],
    "Translation": ""
  },
  {
    "Text": [
      "#12P",
      "#00004F",
      "……はい。\u0001",
      "そうありたいと思います。\u0002"
    ],
    "Translation": ""
  },
  {
    "Text": "bu04600.itp",
    "Translation": ""
  },
  {
    "Text": "bu04601.itp",
    "Translation": ""
  },
  {
    "Text": "c0470:Layer10",
    "Translation": ""
  },
  {
    "Text": "puropera_00",
    "Translation": ""
  },
  {
    "Text": "puropera_01",
    "Translation": ""
  },
  {
    "Text": "puropera_02",
    "Translation": ""
  },
  {
    "Text": "puropera_03",
    "Translation": ""
  },
  {
    "Text": [
      "#03506F",
      "なんだなんだ～、またドギかよ。\u0002",
      "\u0003",
      "#03501F",
      "たまにはフィーナも\u0001",
      "出てくれないとつまんねぇぜ。\u0002"
    ],
    "Translation": ""
  },
  {
    "Text": [
      "#00013F",
      "#12P",
      "──レクターさん。\u0001",
      "もう逃げられませんよ。\u0002"
    ],
    "Translation": ""
  },
  {
    "Text": [
      "#00101F",
      "#6P",
      "いいかげん、観念して\u0001",
      "身元を明らかにしてください。\u0002"
    ],
    "Translation": ""
  },
  {
    "Text": [
      "#03503F",
      "#5P",
      "身元ねェ～。\u0002",
      "\u0003",
      "#03510F",
      "ミモト、ミモト……\u0001",
      "どれがいいかなぁっと。\u0002"
    ],
    "Translation": ""
  },
  {
    "Text": [
      "#00006F",
      "#12P",
      "……あからさまに\u0001",
      "誤魔化そうとしないで下さい。\u0002"
    ],
    "Translation": ""
  },
  {
    "Text": [
      "#03504F",
      "そうだな……\u0002",
      "\u0003",
      "#03500F",
      "イエス・オア・ノーで答えるから\u0001",
      "何でも質問してくれよ。\u0002"
    ],
    "Translation": ""
  },
  {
    "Text": [
      "#00003F",
      "#12P",
      "……分かりました。\u0001",
      "それでは質問させて頂きます。\u0002",
      "\u0003",
      "#00001F",
      "──帝国政府二等書記官、\u0001",
      "レクター・アランドール殿で\u0001",
      "間違いありませんか？\u0002"
    ],
    "Translation": ""
  },
  {
    "Text": [
      "#03504F",
      "イエス。\u0002"
    ],
    "Translation": ""
  },
  {
    "Text": [
      "#00013F",
      "#12P",
      "帝国軍情報局に所属する\u0001",
      "特務大尉でもいらっしゃる？\u0002"
    ],
    "Translation": ""
  },
  {
    "Text": [
      "#03504F",
      "イエスだ。\u0002"
    ],
    "Translation": ""
  },
  {
    "Text": [
      "#00008F",
      "#12P",
      "（あっさり認めるのか……）\u0002"
    ],
    "Translation": ""
  },
  {
    "Text": [
      "#00103F",
      "#6P",
      "……では、私の方からも。\u0002",
      "\u0003",
      "#00101F",
      "今回の訪問は、帝国政府の\u0001",
      "意向を受けてのものですか？\u0002"
    ],
    "Translation": ""
  },
  {
    "Text": [
      "#03501F",
      "ノーであり、イエスでもある。\u0002"
    ],
    "Translation": ""
  },
  {
    "Text": [
      "#00101F",
      "#6P",
      "１ヶ月以上の滞在を\u0001",
      "予定されていますか？\u0002"
    ],
    "Translation": ""
  },
  {
    "Text": [
      "#03504F",
      "フフ……\u0002",
      "\u0003",
      "#03502F",
      "答えはノーだ。\u0001",
      "一週間くらいで帰るぜ。\u0002"
    ],
    "Translation": ""
  },
  {
    "Text": [
      "#00013F",
      "（ここまでか……）\u0002"
    ],
    "Translation": ""
  },
  {
    "Text": [
      "#00108F",
      "（ええ……\u0001",
      "  これ以上は無理ね。）\u0002"
    ],
    "Translation": ""
  },
  {
    "Text": [
      "#00003F",
      "#12P",
      "──お手数をかけました。\u0001",
      "アランドール大尉。\u0002"
    ],
    "Translation": ""
  },
  {
    "Text": [
      "#00100F",
      "#6P",
      "ご協力、感謝いたします。\u0002"
    ],
    "Translation": ""
  },
  {
    "Text": [
      "#03506F",
      "ああ、別にいいけどよー。\u0002",
      "\u0003",
      "#03505F",
      "そういや、あのチビッ子は元気か？\u0001",
      "アンタらが引き取ったんだよな？\u0002"
    ],
    "Translation": ""
  },
  {
    "Text": [
      "#00005F",
      "#12P",
      "えっと、キーアの事ですよね？\u0002",
      "\u0003",
      "#00012F",
      "ええ、おかげさまで\u0001",
      "元気一杯に暮らしています。\u0002"
    ],
    "Translation": ""
  },
  {
    "Text": [
      "#00104F",
      "#6P",
      "……その節は\u0001",
      "ありがとうございました。\u0002"
    ],
    "Translation": ""
  },
  {
    "Text": [
      "#10302F",
      "#6P",
      "フフ、僕たちを逃がすのに\u0001",
      "協力してくれたもんね。\u0002"
    ],
    "Translation": ""
  },
  {
    "Text": [
      "#03504F",
      "ん～、何のことだ？\u0001",
      "オレはクロと遊んでただけだぜ。\u0002",
      "\u0003",
      "#03502F",
      "そういや、ハルトマンのオッサン、\u0001",
      "結局捕まっちまったんだってな？\u0002",
      "\u0003",
      "まあ、妙なのに連れ回されてたし、\u0001",
      "無事に保護されてよかったぜ。\u0002"
    ],
    "Translation": ""
  },
  {
    "Text": [
      "#00001F",
      "#12P",
      "……何でそんなことまで。\u0002"
    ],
    "Translation": ""
  },
  {
    "Text": [
      "#10108F",
      "#6P",
      "あの２人を逮捕してから\u0001",
      "３日も経っていないのに……\u0002"
    ],
    "Translation": ""
  },
  {
    "Text": [
      "#03503F",
      "ま、そのあたりの確認も\u0001",
      "オレが来た目的の一つだからな。\u0002",
      "\u0003",
      "#03501F",
      "ちなみに他の目的は──\u0002"
    ],
    "Translation": ""
  },
  {
    "Text": "少女の声",
    "Translation": ""
  },
  {
    "Text": [
      "#3936V",
      "#1P",
      "#30W",
      "あ～、いたいた！\u0002"
    ],
    "Translation": ""
  },
  {
    "Text": "少女の声",
    "Translation": ""
  },
  {
    "Text": [
      "#3937V",
      "#1P",
      "#30W",
      "こんな所で何やってんのさー。\u0002"
    ],
    "Translation": ""
  },
  {
    "Text": "heri_04a",
    "Translation": ""
  },
  {
    "Text": "poul_02a",
    "Translation": ""
  },
  {
    "Text": "nuki_04",
    "Translation": ""
  },
  {
    "Text": "white00",
    "Translation": ""
  },
  {
    "Text": [
      "#04601F",
      "#3970V",
      "#11P",
      "#30W",
      "アルカンシェルのチケットを\u0001",
      "手配してくれるんだろー？\u0002",
      "\u0003",
      "#3971V",
      "それで、どうなったのさ～！\u0002"
    ],
    "Translation": ""
  },
  {
    "Text": [
      "#03509F",
      "#6P",
      "うむ、今日の夜公演の\u0001",
      "貴賓席を確保してやったぞ。\u0002",
      "\u0003",
      "せいぜい感謝するがよい。\u0002"
    ],
    "Translation": ""
  },
  {
    "Text": [
      "#04602F",
      "#11P",
      "ホント！？\u0002",
      "\u0003",
      "#04612F",
      "えへへ、サンキュ！\u0001",
      "前から見たかったんだよねっ！\u0002"
    ],
    "Translation": ""
  },
  {
    "Text": [
      "#00005F",
      "#5P",
      "（……誰だ……？）\u0002"
    ],
    "Translation": ""
  },
  {
    "Text": [
      "#00105F",
      "#6P",
      "（まだ若いみたいだけど……）\u0002"
    ],
    "Translation": ""
  },
  {
    "Text": [
      "#04605F",
      "#11P",
      "あれ……？\u0002",
      "\u0003",
      "………………………………\u0002"
    ],
    "Translation": ""
  },
  {
    "Text": [
      "#00012F",
      "#5P",
      "えっと……何かな？\u0002"
    ],
    "Translation": ""
  },
  {
    "Text": [
      "フーン……\u0001",
      "お兄さん、匂いがするね。\u0002",
      "\u0003",
      "懐かしい匂いだ。\u0002"
    ],
    "Translation": ""
  },
  {
    "Text": [
      "#00005F",
      "#5P",
      "え……\u0002"
    ],
    "Translation": ""
  },
  {
    "Text": [
      "#04609F",
      "#3972V",
      "#11P",
      "あーむっ。\u0002"
    ],
    "Translation": ""
  },
  {
    "Text": "",
    "Translation": ""
  },
  {
    "Text": [
      "\u0007\u0005",
      "少女はロイドの耳たぶに軽く噛",
      "#2Rかじ#",
      "り付いた。",
      "\u0007\u0000",
      "\u0002"
    ],
    "Translation": ""
  },
  {
    "Text": [
      "#00011F",
      "#5P",
      "！！！？？？？\u0002"
    ],
    "Translation": ""
  },
  {
    "Text": [
      "#00111F",
      "#6P",
      "ちょ、ちょっと！？\u0002"
    ],
    "Translation": ""
  },
  {
    "Text": [
      "#10111F",
      "#6P",
      "え、ええええ～っ！？\u0002"
    ],
    "Translation": ""
  },
  {
    "Text": [
      "#10302F",
      "#12P",
      "ヒュウ♪\u0002"
    ],
    "Translation": ""
  },
  {
    "Text": [
      "#00007F",
      "#5P",
      "い、いきなり何を……！？\u0002"
    ],
    "Translation": ""
  },
  {
    "Text": "赤毛の少女",
    "Translation": ""
  },
  {
    "Text": [
      "#04612F",
      "#11P",
      "えへへ、ご馳走さま㈱\u0002",
      "\u0003",
      "#04602F",
      "うん、やっぱり\u0001",
      "かすかに匂いがするなぁ。\u0002",
      "\u0003",
      "そっちの２人からは\u0001",
      "ほとんど匂わないけど……\u0002"
    ],
    "Translation": ""
  },
  {
    "Text": [
      "#04605F",
      "#11P",
      "──あ！\u0001",
      "お姉さんはちょっとするね！？\u0002"
    ],
    "Translation": ""
  },
  {
    "Text": [
      "#00105F",
      "#6P",
      "え……\u0002"
    ],
    "Translation": ""
  },
  {
    "Text": [
      "#00115F",
      "#3391V",
      "#4S",
      "#5P",
      "きゃあああああっ！？\u0002"
    ],
    "Translation": ""
  },
  {
    "Text": [
      "#00011F",
      "#11P",
      "エ、エリィ！？\u0002"
    ],
    "Translation": ""
  },
  {
    "Text": [
      "#10111F",
      "#5P",
      "い、いつの間に後ろに？\u0002"
    ],
    "Translation": ""
  },
  {
    "Text": [
      "#04611F",
      "#3938V",
      "#5P",
      "#30W",
      "お姉さん、おっきいねー。\u0002",
      "\u0003",
      "#04609F",
      "#3939V",
      "シャーリィはペタンだから\u0001",
      "うらやましいよ㈱\u0002"
    ],
    "Translation": ""
  },
  {
    "Text": [
      "#00112F",
      "#3392V",
      "#5P",
      "#40W",
      "ちょ、ちょっと\u0001",
      "やめてちょうだい……！\u0002",
      "\u0003",
      "#00113F",
      "#3393V",
      "あうんっ……！\u0001",
      "ど、どうしてこんな……！\u0002"
    ],
    "Translation": ""
  },
  {
    "Text": [
      "#10114F",
      "#5P",
      "な、な、な……\u0002"
    ],
    "Translation": ""
  },
  {
    "Text": [
      "#10309F",
      "#6P",
      "アハハ、いい光景だなぁ。\u0002"
    ],
    "Translation": ""
  },
  {
    "Text": [
      "#00012F",
      "#11P",
      "た、確かに……じゃなくて！\u0002",
      "\u0003",
      "#00007F",
      "ちょっと君！\u0001",
      "いきなり何してるんだ！？\u0002"
    ],
    "Translation": ""
  },
  {
    "Text": [
      "#11P",
      "#03509F",
      "ハハッ、やりたい放題だな。\u0002",
      "\u0003",
      "#03502F",
      "それ以上やると\u0001",
      "セクハラになっちまうぞ～？\u0002"
    ],
    "Translation": ""
  },
  {
    "Text": [
      "#04605F",
      "#5P",
      "セクハラじゃないよー。\u0001",
      "スキンシップだってば。\u0002"
    ],
    "Translation": ""
  },
  {
    "Text": [
      "#00107F",
      "#5P",
      "#4S",
      "じゅ、十分セクハラですっ！\u0002"
    ],
    "Translation": ""
  },
  {
    "Text": [
      "#5P",
      "#00113F",
      "はあはあはあ……\u0002"
    ],
    "Translation": ""
  },
  {
    "Text": [
      "#10111F",
      "#5P",
      "エ、エリィさん。\u0002"
    ],
    "Translation": ""
  },
  {
    "Text": [
      "#00011F",
      "#11P",
      "だ、大丈夫か？\u0002"
    ],
    "Translation": ""
  },
  {
    "Text": [
      "#03510F",
      "#5P",
      "うむ、それでは\u0001",
      "オレたちは失礼しよう。\u0002",
      "\u0003",
      "#03509F",
      "ミシュラムのテーマパークで\u0001",
      "夜まで遊び倒すんでな。\u0002"
    ],
    "Translation": ""
  },
  {
    "Text": "シャーリィ",
    "Translation": ""
  },
  {
    "Text": [
      "#04612F",
      "#3940V",
      "#5P",
      "#30W",
      "それじゃ、またね～！\u0002"
    ],
    "Translation": ""
  },
  {
    "Text": [
      "#00013F",
      "#5P",
      "な、何だったんだ……？\u0002"
    ],
    "Translation": ""
  },
  {
    "Text": [
      "#10106F",
      "#5P",
      "つ、つい\u0001",
      "見逃しちゃいましたけど……\u0002"
    ],
    "Translation": ""
  },
  {
    "Text": [
      "#10302F",
      "#5P",
      "フフ、強烈な子だったね。\u0002",
      "\u0003",
      "#10309F",
      "１５、６歳くらいかな？\u0001",
      "なかなか良い仕事するじゃない。\u0002"
    ],
    "Translation": ""
  },
  {
    "Text": [
      "#00107F",
      "#5P",
      "#4S",
      "良い仕事じゃありません！\u0002"
    ],
    "Translation": ""
  },
  {
    "Text": [
      "#00106F",
      "#5P",
      "#30W",
      "ううっ……\u0001",
      "どうして私がこんな目に……\u0002"
    ],
    "Translation": ""
  },
  {
    "Text": [
      "#00012F",
      "#11P",
      "えっと……災難だったな。\u0002"
    ],
    "Translation": ""
  },
  {
    "Text": [
      "#10112F",
      "#5P",
      "ま、まあ女の子同士だし\u0001",
      "そこまで深刻にならなくても……\u0002"
    ],
    "Translation": ""
  },
  {
    "Text": [
      "#10305F",
      "#12P",
      "それに君、マリアベル嬢に\u0001",
      "揉まれ慣れてるんじゃないの？\u0002"
    ],
    "Translation": ""
  },
  {
    "Text": [
      "#00115F",
      "#5P",
      "#5S",
      "も、揉まれ慣れてません！\u0002"
    ],
    "Translation": ""
  },
  {
    "Text": "",
    "Translation": ""
  },
  {
    "Text": [
      "\u0007\u0005",
      "その後、ロイドたちは\u0001",
      "警察本部に戻って一課を呼び出し……\u0002",
      "\u0003",
      "黒月の動向と合わせて\u0001",
      "レクターに関する報告を行った。",
      "\u0007\u0000",
      "\u0002"
    ],
    "Translation": ""
  },
  {
    "Text": "white00",
    "Translation": ""
  }
]